PteroDark/__init__.py
PteroDark/main.py
PteroDark-1.0.0.dist-info/LICENSE
PteroDark-1.0.0.dist-info/METADATA
PteroDark-1.0.0.dist-info/WHEEL
PteroDark-1.0.0.dist-info/top_level.txt
PteroDark-1.0.0.dist-info/RECORD
