Metadata-Version: 2.1
Name: PteroDark
Version: 1.0.0
Summary: Pterodactyl API wrapper
Home-page: https://github.com/LeaveHosting/PteroDark
Author: LeaveHosting
Author-email: leavehosting@gmail.com
Project-URL: Documentation, https://github.com/LeaveHosting/PteroDark/README.md
Keywords: example python
Classifier: Programming Language :: Python :: 3.11
Classifier: License :: OSI Approved :: MIT License
Classifier: Operating System :: OS Independent
Requires-Python: >=3.11
License-File: LICENSE
Requires-Dist: requests >=2.25.1
